kube_shields/__init__.py
kube_shields/kubernetes.py
kube_shields/web.py
kube_shields/snowflakes/__init__.py
kube_shields/templates/index.html
kube_shields-0.0.6.dist-info/DESCRIPTION.rst
kube_shields-0.0.6.dist-info/METADATA
kube_shields-0.0.6.dist-info/RECORD
kube_shields-0.0.6.dist-info/WHEEL
kube_shields-0.0.6.dist-info/entry_points.txt
kube_shields-0.0.6.dist-info/metadata.json
kube_shields-0.0.6.dist-info/top_level.txt
