Metadata-Version: 2.0
Name: kube-shields
Version: 0.0.6
Summary: kube shields flask frontend.
Home-page: https://github.com/ccpgames/kube_shields/
Author: Adam Talsma
Author-email: se-adam.talsma@ccpgames.com
License: UNKNOWN
Download-URL: https://github.com/ccpgames/kube_shields/
Platform: UNKNOWN
Classifier: Development Status :: 5 - Production/Stable
Classifier: Environment :: Web Environment
Classifier: Framework :: Flask
Classifier: Operating System :: POSIX :: Linux
Classifier: Programming Language :: Python :: 2.7
Classifier: License :: OSI Approved :: MIT License
Requires-Dist: Flask (>=0.10.0)
Requires-Dist: requests (>=2.9.0)
Provides-Extra: deploy
Requires-Dist: PasteDeploy; extra == 'deploy'
Requires-Dist: paste; extra == 'deploy'
Requires-Dist: uwsgi; extra == 'deploy'
